{"frameRate":24,"name":"background_chengbao","version":"5.5","compatibleVersion":"5.5","armature":[{"type":"Armature","frameRate":24,"name":"Armature","aabb":{"x":-422.93,"y":-441.01,"width":846.11,"height":882},"bone":[{"name":"root"},{"name":"bone","parent":"root","transform":{"x":1.4069,"y":385.2958}},{"name":"huo_0000221111","parent":"bone","transform":{"x":92.013,"y":-292.1272}},{"name":"huo_0000221111111","parent":"bone","transform":{"x":92.4793,"y":-485.7943}},{"name":"huo_000022111111","parent":"bone","transform":{"x":322.7495,"y":-485.7424}},{"name":"huo_000022111121","parent":"bone","transform":{"x":-323.0953,"y":-293.4788}},{"name":"huo_00002211112","parent":"bone","transform":{"x":-92.6357,"y":-293.0405}},{"name":"huo_00002211111","parent":"bone","transform":{"x":323.0134,"y":-292.1227}},{"name":"huo_00002211111111","parent":"bone","transform":{"x":-91.0038,"y":-486.2331}},{"name":"huo_000022111111111","parent":"bone","transform":{"x":-322.8041,"y":-485.4486}}],"slot":[{"displayIndex":3,"name":"01","parent":"root"},{"displayIndex":2,"name":"huo_00002221111","parent":"huo_0000221111"},{"displayIndex":2,"name":"huo_000022211111","parent":"huo_00002211111"},{"displayIndex":2,"name":"huo_000022211112","parent":"huo_00002211112"},{"displayIndex":2,"name":"huo_0000222111121","parent":"huo_000022111121"},{"displayIndex":2,"name":"huo_0000222111111","parent":"huo_000022111111"},{"displayIndex":2,"name":"huo_00002221111111","parent":"huo_0000221111111"},{"displayIndex":2,"name":"huo_000022211111111","parent":"huo_00002211111111"},{"displayIndex":2,"name":"huo_0000222111111111","parent":"huo_000022111111111"}],"skin":[{"slot":[{"name":"huo_000022211112","display":[{"name":"huo/huo_00002","transform":{"x":-1.24,"y":-40.3,"scX":0.6}},{"name":"huo/huo_3","transform":{"x":-1.24,"y":-40.3,"scX":0.6},"path":"huo/huo_00001"},{"name":"huo/huo_4","transform":{"x":-1.24,"y":-40.3,"scX":0.6},"path":"huo/huo_00000"}]},{"name":"huo_000022211111","display":[{"name":"huo/huo_00002","transform":{"x":-1.24,"y":-40.3,"scX":0.6}},{"name":"huo/huo_3","transform":{"x":-1.24,"y":-40.3,"scX":0.6},"path":"huo/huo_00001"},{"name":"huo/huo_4","transform":{"x":-1.24,"y":-40.3,"scX":0.6},"path":"huo/huo_00000"}]},{"name":"huo_00002221111","display":[{"name":"huo/huo_00002","transform":{"x":-1.24,"y":-40.3,"scX":0.6}},{"name":"huo/huo_3","transform":{"x":-1.24,"y":-40.3,"scX":0.6},"path":"huo/huo_00001"},{"name":"huo/huo_4","transform":{"x":-1.24,"y":-40.3,"scX":0.6},"path":"huo/huo_00000"}]},{"name":"huo_0000222111111111","display":[{"name":"huo/huo_00002","transform":{"x":-1.24,"y":-40.3,"scX":0.6}},{"name":"huo/huo_3","transform":{"x":-1.24,"y":-40.3,"scX":0.6},"path":"huo/huo_00001"},{"name":"huo/huo_4","transform":{"x":-1.24,"y":-40.3,"scX":0.6},"path":"huo/huo_00000"}]},{"name":"01","display":[{"name":"01","transform":{"x":-0.01,"y":-0.01}},{"name":"2","transform":{"x":-0.01,"y":-0.01},"path":"02"},{"name":"3","transform":{"x":-0.01,"y":-0.01},"path":"03"},{"name":"4","transform":{"x":-0.01,"y":-0.01},"path":"04"}]},{"name":"huo_000022211111111","display":[{"name":"huo/huo_00002","transform":{"x":-1.24,"y":-40.3,"scX":0.6}},{"name":"huo/huo_3","transform":{"x":-1.24,"y":-40.3,"scX":0.6},"path":"huo/huo_00001"},{"name":"huo/huo_4","transform":{"x":-1.24,"y":-40.3,"scX":0.6},"path":"huo/huo_00000"}]},{"name":"huo_00002221111111","display":[{"name":"huo/huo_00002","transform":{"x":-1.24,"y":-40.3,"scX":0.6}},{"name":"huo/huo_3","transform":{"x":-1.24,"y":-40.3,"scX":0.6},"path":"huo/huo_00001"},{"name":"huo/huo_4","transform":{"x":-1.24,"y":-40.3,"scX":0.6},"path":"huo/huo_00000"}]},{"name":"huo_0000222111111","display":[{"name":"huo/huo_00002","transform":{"x":-1.24,"y":-40.3,"scX":0.6}},{"name":"huo/huo_3","transform":{"x":-1.24,"y":-40.3,"scX":0.6},"path":"huo/huo_00001"},{"name":"huo/huo_4","transform":{"x":-1.24,"y":-40.3,"scX":0.6},"path":"huo/huo_00000"}]},{"name":"huo_0000222111121","display":[{"name":"huo/huo_00002","transform":{"x":-1.24,"y":-40.3,"scX":0.6}},{"name":"huo/huo_3","transform":{"x":-1.24,"y":-40.3,"scX":0.6},"path":"huo/huo_00001"},{"name":"huo/huo_4","transform":{"x":-1.24,"y":-40.3,"scX":0.6},"path":"huo/huo_00000"}]}]}],"animation":[{"duration":49,"playTimes":0,"name":"type1","slot":[{"name":"huo_00002221111","displayFrame":[{"duration":4,"value":2},{"duration":4,"value":1},{"duration":5},{"duration":4,"value":2},{"duration":4,"value":1},{"duration":4},{"duration":4,"value":2},{"duration":4,"value":1},{"duration":4},{"duration":4,"value":2},{"duration":3,"value":1},{"duration":4},{"value":2}]},{"name":"huo_000022211111","displayFrame":[{"duration":4,"value":1},{"duration":5},{"duration":4,"value":2},{"duration":4,"value":1},{"duration":4},{"duration":4,"value":2},{"duration":4,"value":1},{"duration":4},{"duration":4,"value":2},{"duration":3,"value":1},{"duration":4},{"duration":5,"value":2},{"duration":0,"value":1}]},{"name":"huo_000022211112","displayFrame":[{"duration":4,"value":1},{"duration":5},{"duration":4,"value":2},{"duration":4,"value":1},{"duration":4},{"duration":4,"value":2},{"duration":4,"value":1},{"duration":4},{"duration":4,"value":2},{"duration":3,"value":1},{"duration":4},{"duration":4,"value":2},{"value":1}]},{"name":"huo_0000222111121","displayFrame":[{"duration":5},{"duration":4,"value":2},{"duration":4,"value":1},{"duration":4},{"duration":4,"value":2},{"duration":4,"value":1},{"duration":4},{"duration":4,"value":2},{"duration":3,"value":1},{"duration":4},{"duration":4,"value":2},{"duration":4,"value":1},{}]},{"name":"huo_0000222111111","displayFrame":[{"duration":4,"value":2},{"duration":4,"value":1},{"duration":5},{"duration":4,"value":2},{"duration":4,"value":1},{"duration":4},{"duration":4,"value":2},{"duration":4,"value":1},{"duration":4},{"duration":4,"value":2},{"duration":3,"value":1},{"duration":4},{"value":2}]},{"name":"huo_00002221111111","displayFrame":[{"duration":5},{"duration":4,"value":2},{"duration":4,"value":1},{"duration":4},{"duration":4,"value":2},{"duration":4,"value":1},{"duration":4},{"duration":4,"value":2},{"duration":3,"value":1},{"duration":4},{"duration":4,"value":2},{"duration":4,"value":1},{}]},{"name":"huo_000022211111111","displayFrame":[{"duration":4,"value":1},{"duration":5},{"duration":4,"value":2},{"duration":4,"value":1},{"duration":4},{"duration":4,"value":2},{"duration":4,"value":1},{"duration":4},{"duration":4,"value":2},{"duration":3,"value":1},{"duration":4},{"duration":4,"value":2},{"value":1}]},{"name":"huo_0000222111111111","displayFrame":[{"duration":4,"value":2},{"duration":4,"value":1},{"duration":5},{"duration":4,"value":2},{"duration":4,"value":1},{"duration":4},{"duration":4,"value":2},{"duration":4,"value":1},{"duration":4},{"duration":4,"value":2},{"duration":3,"value":1},{"duration":4},{"value":2}]},{"name":"01","displayFrame":[{"duration":49}]}]},{"duration":49,"playTimes":0,"name":"type2","slot":[{"name":"huo_00002221111","displayFrame":[{"duration":4,"value":2},{"duration":4,"value":1},{"duration":5},{"duration":4,"value":2},{"duration":4,"value":1},{"duration":4},{"duration":4,"value":2},{"duration":4,"value":1},{"duration":4},{"duration":4,"value":2},{"duration":3,"value":1},{"duration":4},{"value":2}]},{"name":"huo_000022211111","displayFrame":[{"duration":4,"value":1},{"duration":5},{"duration":4,"value":2},{"duration":4,"value":1},{"duration":4},{"duration":4,"value":2},{"duration":4,"value":1},{"duration":4},{"duration":4,"value":2},{"duration":3,"value":1},{"duration":4},{"duration":5,"value":2},{"duration":0,"value":1}]},{"name":"huo_000022211112","displayFrame":[{"duration":4,"value":1},{"duration":5},{"duration":4,"value":2},{"duration":4,"value":1},{"duration":4},{"duration":4,"value":2},{"duration":4,"value":1},{"duration":4},{"duration":4,"value":2},{"duration":3,"value":1},{"duration":4},{"duration":4,"value":2},{"value":1}]},{"name":"huo_0000222111121","displayFrame":[{"duration":5},{"duration":4,"value":2},{"duration":4,"value":1},{"duration":4},{"duration":4,"value":2},{"duration":4,"value":1},{"duration":4},{"duration":4,"value":2},{"duration":3,"value":1},{"duration":4},{"duration":4,"value":2},{"duration":4,"value":1},{}]},{"name":"huo_0000222111111","displayFrame":[{"duration":4,"value":2},{"duration":4,"value":1},{"duration":5},{"duration":4,"value":2},{"duration":4,"value":1},{"duration":4},{"duration":4,"value":2},{"duration":4,"value":1},{"duration":4},{"duration":4,"value":2},{"duration":3,"value":1},{"duration":4},{"value":2}]},{"name":"huo_00002221111111","displayFrame":[{"duration":5},{"duration":4,"value":2},{"duration":4,"value":1},{"duration":4},{"duration":4,"value":2},{"duration":4,"value":1},{"duration":4},{"duration":4,"value":2},{"duration":3,"value":1},{"duration":4},{"duration":4,"value":2},{"duration":4,"value":1},{}]},{"name":"huo_000022211111111","displayFrame":[{"duration":4,"value":1},{"duration":5},{"duration":4,"value":2},{"duration":4,"value":1},{"duration":4},{"duration":4,"value":2},{"duration":4,"value":1},{"duration":4},{"duration":4,"value":2},{"duration":3,"value":1},{"duration":4},{"duration":4,"value":2},{"value":1}]},{"name":"huo_0000222111111111","displayFrame":[{"duration":4,"value":2},{"duration":4,"value":1},{"duration":5},{"duration":4,"value":2},{"duration":4,"value":1},{"duration":4},{"duration":4,"value":2},{"duration":4,"value":1},{"duration":4},{"duration":4,"value":2},{"duration":3,"value":1},{"duration":4},{"value":2}]},{"name":"01","displayFrame":[{"duration":49,"value":1}]}]},{"duration":49,"playTimes":0,"name":"type3","slot":[{"name":"huo_00002221111","displayFrame":[{"duration":4,"value":2},{"duration":4,"value":1},{"duration":5},{"duration":4,"value":2},{"duration":4,"value":1},{"duration":4},{"duration":4,"value":2},{"duration":4,"value":1},{"duration":4},{"duration":4,"value":2},{"duration":3,"value":1},{"duration":4},{"value":2}]},{"name":"huo_000022211111","displayFrame":[{"duration":4,"value":1},{"duration":5},{"duration":4,"value":2},{"duration":4,"value":1},{"duration":4},{"duration":4,"value":2},{"duration":4,"value":1},{"duration":4},{"duration":4,"value":2},{"duration":3,"value":1},{"duration":4},{"duration":5,"value":2},{"duration":0,"value":1}]},{"name":"huo_000022211112","displayFrame":[{"duration":4,"value":1},{"duration":5},{"duration":4,"value":2},{"duration":4,"value":1},{"duration":4},{"duration":4,"value":2},{"duration":4,"value":1},{"duration":4},{"duration":4,"value":2},{"duration":3,"value":1},{"duration":4},{"duration":4,"value":2},{"value":1}]},{"name":"huo_0000222111121","displayFrame":[{"duration":5},{"duration":4,"value":2},{"duration":4,"value":1},{"duration":4},{"duration":4,"value":2},{"duration":4,"value":1},{"duration":4},{"duration":4,"value":2},{"duration":3,"value":1},{"duration":4},{"duration":4,"value":2},{"duration":4,"value":1},{}]},{"name":"huo_0000222111111","displayFrame":[{"duration":4,"value":2},{"duration":4,"value":1},{"duration":5},{"duration":4,"value":2},{"duration":4,"value":1},{"duration":4},{"duration":4,"value":2},{"duration":4,"value":1},{"duration":4},{"duration":4,"value":2},{"duration":3,"value":1},{"duration":4},{"value":2}]},{"name":"huo_00002221111111","displayFrame":[{"duration":5},{"duration":4,"value":2},{"duration":4,"value":1},{"duration":4},{"duration":4,"value":2},{"duration":4,"value":1},{"duration":4},{"duration":4,"value":2},{"duration":3,"value":1},{"duration":4},{"duration":4,"value":2},{"duration":4,"value":1},{}]},{"name":"huo_000022211111111","displayFrame":[{"duration":4,"value":1},{"duration":5},{"duration":4,"value":2},{"duration":4,"value":1},{"duration":4},{"duration":4,"value":2},{"duration":4,"value":1},{"duration":4},{"duration":4,"value":2},{"duration":3,"value":1},{"duration":4},{"duration":4,"value":2},{"value":1}]},{"name":"huo_0000222111111111","displayFrame":[{"duration":4,"value":2},{"duration":4,"value":1},{"duration":5},{"duration":4,"value":2},{"duration":4,"value":1},{"duration":4},{"duration":4,"value":2},{"duration":4,"value":1},{"duration":4},{"duration":4,"value":2},{"duration":3,"value":1},{"duration":4},{"value":2}]},{"name":"01","displayFrame":[{"duration":49,"value":2}]}]},{"duration":49,"playTimes":0,"name":"type4","slot":[{"name":"huo_00002221111","displayFrame":[{"duration":4,"value":2},{"duration":4,"value":1},{"duration":5},{"duration":4,"value":2},{"duration":4,"value":1},{"duration":4},{"duration":4,"value":2},{"duration":4,"value":1},{"duration":4},{"duration":4,"value":2},{"duration":3,"value":1},{"duration":4},{"value":2}]},{"name":"huo_000022211111","displayFrame":[{"duration":4,"value":1},{"duration":5},{"duration":4,"value":2},{"duration":4,"value":1},{"duration":4},{"duration":4,"value":2},{"duration":4,"value":1},{"duration":4},{"duration":4,"value":2},{"duration":3,"value":1},{"duration":4},{"duration":5,"value":2},{"duration":0,"value":1}]},{"name":"huo_000022211112","displayFrame":[{"duration":4,"value":1},{"duration":5},{"duration":4,"value":2},{"duration":4,"value":1},{"duration":4},{"duration":4,"value":2},{"duration":4,"value":1},{"duration":4},{"duration":4,"value":2},{"duration":3,"value":1},{"duration":4},{"duration":4,"value":2},{"value":1}]},{"name":"huo_0000222111121","displayFrame":[{"duration":5},{"duration":4,"value":2},{"duration":4,"value":1},{"duration":4},{"duration":4,"value":2},{"duration":4,"value":1},{"duration":4},{"duration":4,"value":2},{"duration":3,"value":1},{"duration":4},{"duration":4,"value":2},{"duration":4,"value":1},{}]},{"name":"huo_0000222111111","displayFrame":[{"duration":4,"value":2},{"duration":4,"value":1},{"duration":5},{"duration":4,"value":2},{"duration":4,"value":1},{"duration":4},{"duration":4,"value":2},{"duration":4,"value":1},{"duration":4},{"duration":4,"value":2},{"duration":3,"value":1},{"duration":4},{"value":2}]},{"name":"huo_00002221111111","displayFrame":[{"duration":5},{"duration":4,"value":2},{"duration":4,"value":1},{"duration":4},{"duration":4,"value":2},{"duration":4,"value":1},{"duration":4},{"duration":4,"value":2},{"duration":3,"value":1},{"duration":4},{"duration":4,"value":2},{"duration":4,"value":1},{}]},{"name":"huo_000022211111111","displayFrame":[{"duration":4,"value":1},{"duration":5},{"duration":4,"value":2},{"duration":4,"value":1},{"duration":4},{"duration":4,"value":2},{"duration":4,"value":1},{"duration":4},{"duration":4,"value":2},{"duration":3,"value":1},{"duration":4},{"duration":4,"value":2},{"value":1}]},{"name":"huo_0000222111111111","displayFrame":[{"duration":4,"value":2},{"duration":4,"value":1},{"duration":5},{"duration":4,"value":2},{"duration":4,"value":1},{"duration":4},{"duration":4,"value":2},{"duration":4,"value":1},{"duration":4},{"duration":4,"value":2},{"duration":3,"value":1},{"duration":4},{"value":2}]}]}],"defaultActions":[{"gotoAndPlay":"type1"}]}]}