{"frameRate":24,"name":"loading","version":"5.5","compatibleVersion":"5.5","armature":[{"type":"Armature","frameRate":24,"name":"Armature","aabb":{"x":-42.57,"y":-42.51,"width":85,"height":85},"bone":[{"name":"root"},{"name":"loading","parent":"root","transform":{"x":0.0054,"y":-0.0005}}],"slot":[{"name":"di","parent":"loading"},{"name":"dian","parent":"loading"},{"name":"dian2","parent":"loading"},{"name":"dian21","parent":"loading"},{"name":"dian211","parent":"loading"},{"name":"dian2111","parent":"loading"},{"name":"dian21111","parent":"loading"},{"name":"dian211111","parent":"loading"}],"skin":[{"slot":[{"name":"dian21111","display":[{"name":"dian","transform":{"x":-21.74,"y":4.12}}]},{"name":"dian211","display":[{"name":"dian","transform":{"x":7.89,"y":18.94}}]},{"name":"di","display":[{"name":"di","transform":{"x":-0.08,"y":-0.01}}]},{"name":"dian211111","display":[{"name":"dian","transform":{"x":-17.61,"y":-13.28}}]},{"name":"dian2","display":[{"name":"dian","transform":{"x":15.72,"y":-13.06}}]},{"name":"dian","display":[{"name":"dian","transform":{"x":-1.09,"y":-21.19}}]},{"name":"dian2111","display":[{"name":"dian","transform":{"x":-10.18,"y":19.31}}]},{"name":"dian21","display":[{"name":"dian","transform":{"x":19.6,"y":4.58}}]}]}],"animation":[{"duration":30,"playTimes":0,"name":"newAnimation","slot":[{"name":"dian","colorFrame":[{"duration":7,"tweenEasing":0},{"duration":7,"tweenEasing":0,"value":{"aM":0}},{"duration":16}]},{"name":"dian2","colorFrame":[{"duration":4},{"duration":7,"tweenEasing":0},{"duration":7,"tweenEasing":0,"value":{"aM":0}},{"duration":12}]},{"name":"dian21","colorFrame":[{"duration":7},{"duration":7,"tweenEasing":0},{"duration":6,"tweenEasing":0,"value":{"aM":0}},{"duration":10}]},{"name":"dian211","colorFrame":[{"duration":11},{"duration":7,"tweenEasing":0},{"duration":6,"tweenEasing":0,"value":{"aM":0}},{"duration":6}]},{"name":"dian2111","colorFrame":[{"duration":14},{"duration":6,"tweenEasing":0},{"duration":7,"tweenEasing":0,"value":{"aM":0}},{"duration":3}]},{"name":"dian21111","colorFrame":[{"duration":18},{"duration":6,"tweenEasing":0},{"duration":6,"tweenEasing":0,"value":{"aM":0}},{"duration":0}]},{"name":"dian211111","colorFrame":[{"duration":8,"tweenEasing":0,"value":{"aM":0}},{"duration":16,"tweenEasing":0},{"duration":6,"tweenEasing":0},{"duration":0,"value":{"aM":0}}]}]}],"defaultActions":[{"gotoAndPlay":"newAnimation"}]}]}